{
  "date": "2026-04-13T08:15:30.881196",
  "total": 77,
  "recommandes": 25,
  "reels": [
    {
      "username": "joellperry",
      "url": "https://www.instagram.com/p/DW2iyKnE6w_/",
      "views": 89487,
      "duration": 4.248,
      "caption": "let’s swim! 🌊 \n.\n.\n.\n.\n.\n.\n.\n.\n.\n.\n.\n.\n.\n.\n.\n.\n.\n.\n.\n.\n.\n.\n.\n.\n.\n.\n.\n.\n.\n.\n.\n.\n.\n.\n.\n.\n.\n.\n.\n.\n.\n.\n.",
      "thumbnail": "https://scontent-lga3-2.cdninstagram.com/v/t51.71878-15/657615087_1676278423549469_912689054181924051_n.jpg?stp=dst-jpg_e15_tt6&_nc_ht=scontent-lga3-2.cdninstagram.com&_nc_cat=105&_nc_oc=Q6cZ2gEFBSyCjC-vSo4R2cunaXe2nxfi5su3VUBYAsu7NCdAYUGv5RYZ-2sPpe2IkCLjxbE&_nc_ohc=o84s_rAcP-AQ7kNvwGz3mSS&_nc_gid=SiUs0S1v0Eg90X68zyFiHg&edm=APs17CUBAAAA&ccb=7-5&oh=00_Af1V2FDvrC4wkTDTVzvI62sDRDhMDIl8yP-7KNgs8OJfdA&oe=69E263C9&_nc_sid=10d13b",
      "analyse": {
        "score": 8,
        "recommande": true,
        "style": "sport",
        "raison": "Excellent contenu sport aquatique avec durée parfaite (4.248s), mouvement simple de plongeon/nage, hook visuel fort avec l'action dynamique vers l'eau, style lifestyle sport très adapté au marché français",
        "conseil_kling": "Créer une séquence de plongeon avec motion control : mouvement fluide du corps vers l'eau, éclaboussures naturelles, angle de caméra fixe pour capturer l'action, transition smooth entre la position initiale et l'entrée dans l'eau"
      }
    },
    {
      "username": "joellperry",
      "url": "https://www.instagram.com/p/DW5P0xxDdkj/",
      "views": 49774,
      "duration": 6.338,
      "caption": "Sun’s out, so am I! ☀️ \n.\n.\n.\n.\n.\n.\n.\n.\n.\n.\n.\n.\n.\n.\n.\n.\n.\n.\n.\n.\n.\n.\n.\n.\n.\n.\n.\n.\n.\n.\n.\n.\n.\n.\n.\n.\n.\n.\n",
      "thumbnail": "https://scontent-ord5-1.cdninstagram.com/v/t51.71878-15/670162048_952739447127085_2403667588459998831_n.jpg?stp=dst-jpg_e15_tt6&_nc_ht=scontent-ord5-1.cdninstagram.com&_nc_cat=101&_nc_oc=Q6cZ2gEi4Jy03cKnmr4VWm5rkxyg7nxgZYuoPquL_W7CQ6TMx79YKue_m18sVnR4t_cXYsA&_nc_ohc=dsDZ2lSgVxAQ7kNvwHUOJGw&_nc_gid=tuxxVd4Yq8OFZPNNMJectA&edm=APs17CUBAAAA&ccb=7-5&oh=00_Af2WOhGiUwwpYnLLn5DgazaE8HFBRf8oiGxYL2OoHx184g&oe=69E26CCB&_nc_sid=10d13b",
      "analyse": {
        "score": 8,
        "recommande": true,
        "style": "lifestyle",
        "raison": "Durée parfaite, contenu lifestyle chill avec soleil, mouvement simple reproductible, bon potentiel viral avec message positif",
        "conseil_kling": "Créer un plan fixe ou légèrement mobile d'une personne sortant à l'extérieur avec éclairage naturel ensoleillé, mouvement de marche ou pose décontractée face caméra"
      }
    },
    {
      "username": "joellperry",
      "url": "https://www.instagram.com/p/DWll-AFgCyg/",
      "views": 56517,
      "duration": 13.118,
      "caption": "What color are my eyes? 😍\n.\n.\n.\n.\n.\n.\n.\n.\n.\n.\n.\n.\n.\n.\n.\n.\n.\n.\n.\n.\n.\n.\n.\n.\n.\n.\n.\n.\n.\n.\n.\n.\n.\n.\n.\n.\n.\n",
      "thumbnail": "https://instagram.fluk1-1.fna.fbcdn.net/v/t51.71878-15/657240168_2370619796750260_4362249638507103133_n.jpg?stp=dst-jpg_e15_tt6&_nc_ht=instagram.fluk1-1.fna.fbcdn.net&_nc_cat=104&_nc_oc=Q6cZ2gEt0vU4fINgiS8Ec35JBq3gTPs1XbrZ8e76S7UjGB1asUtBp8jVXQ2Dfs6zfK3Y5P8&_nc_ohc=a1qz4Trjve0Q7kNvwG3LWm6&_nc_gid=6uXEOgJhP-F610aNhT4yeA&edm=APs17CUBAAAA&ccb=7-5&oh=00_Af1zU9XLJBZXop1ifqTFIVtqUqinVcFXUYaTKY8-nC0Kag&oe=69E2732B&_nc_sid=10d13b",
      "analyse": {
        "score": 8,
        "recommande": true,
        "style": "lifestyle",
        "raison": "Durée parfaite, concept simple et viral avec question engageante sur les yeux, regard caméra direct très efficace pour l'engagement",
        "conseil_kling": "Créer un gros plan visage avec zoom progressif sur les yeux, mouvement de caméra lent et fluide, éclairage naturel pour faire ressortir la couleur des yeux"
      }
    },
    {
      "username": "dahyn1xoficial",
      "url": "https://www.instagram.com/p/DWwpIp-DshL/",
      "views": 156830,
      "duration": 11.61,
      "caption": "Taking energy from the sun… ☀️✨\n\n.\n\n.\n\n.\n#reels #cutegirl #eeuu #usa #bellydance",
      "thumbnail": "https://scontent-ord5-1.cdninstagram.com/v/t51.71878-15/660461588_1658588795282581_839611970221190027_n.jpg?stp=dst-jpg_e15_tt6&_nc_ht=scontent-ord5-1.cdninstagram.com&_nc_cat=101&_nc_oc=Q6cZ2gHmYuS0NS1B7vP3mdlHX9tO21DTrLP6qr-SPuChdsEncknSns4ZQ7jUahgfAWXvt9w&_nc_ohc=PqM8iDvt818Q7kNvwEI29Fg&_nc_gid=svCf7-SjJnldcao6OaT9UA&edm=APs17CUBAAAA&ccb=7-5&oh=00_Af11JSgSv8qYiFdNjSobONTqi8zrEGMqA073SxxCms_2MA&oe=69E28D77&_nc_sid=10d13b",
      "analyse": {
        "score": 8,
        "recommande": true,
        "style": "danse",
        "raison": "Danse belly dance fluide en extérieur, durée parfaite, mouvement hypnotique avec bon potentiel viral, pas de parole",
        "conseil_kling": "Générer une femme en tenue décontractée faisant des mouvements de danse du ventre fluides face caméra, éclairage naturel extérieur, mouvement de bras et hanches synchronisé"
      }
    },
    {
      "username": "dahyn1xoficial",
      "url": "https://www.instagram.com/p/DWSg1xRDlkC/",
      "views": 330736,
      "duration": 10.966,
      "caption": "Just a transition… and everything turns red ❤️✨\n\n.\n\n.\n\n.\n\n.\n\n#reels #cutegirl #eeuu #cute #usa",
      "thumbnail": "https://scontent-atl3-1.cdninstagram.com/v/t51.71878-15/658650059_2205274550311206_4687958551220965394_n.jpg?stp=dst-jpg_e15_tt6&_nc_ht=scontent-atl3-1.cdninstagram.com&_nc_cat=106&_nc_oc=Q6cZ2gEqa1KotFJ8TF53GsqUGUpp1HHSeukl4-43pw_UUB3deMztzxBj_D5vyEfug39-mcfhr8eG7ECujrmpRcErHYO0&_nc_ohc=OaZgj9bryDAQ7kNvwHzgbeW&_nc_gid=zndp-wqthp6zo1N0m3u8yA&edm=APs17CUBAAAA&ccb=7-5&oh=00_Af07EIu9peBhxBVjTZfy_ul2cnlS9LshPkPzDbvOrKMeVQ&oe=69E25C29&_nc_sid=10d13b",
      "analyse": {
        "score": 8,
        "recommande": true,
        "style": "lifestyle",
        "raison": "Transition simple et efficace avec changement de couleur rouge, durée parfaite, regard caméra fort, très reproductible",
        "conseil_kling": "Utiliser motion control pour transition fluide entre deux looks/poses, appliquer filter rouge progressif, maintenir regard caméra fixe pendant la transformation"
      }
    },
    {
      "username": "dahyn1xoficial",
      "url": "https://www.instagram.com/p/DWHGh-yjqLD/",
      "views": 54127,
      "duration": 12.9,
      "caption": "Abs don’t just appear on their own… 😮‍🔥\n\n.\n\n.\n\n.\n\n.\n#reels #viral #florida #girl #usa",
      "thumbnail": "https://scontent-phl2-1.cdninstagram.com/v/t51.71878-15/655155903_717023028164257_2471845235487709718_n.jpg?stp=dst-jpg_e15_tt6&_nc_ht=scontent-phl2-1.cdninstagram.com&_nc_cat=101&_nc_oc=Q6cZ2gHuZc_-sU0_X6a_dU3QdwLTS5hKTvMV3QLxHB0_XCMmVwjAIYd8my71ETurzoGjPCA&_nc_ohc=r-LapjcgBfcQ7kNvwE-fIMJ&_nc_gid=5-c4FebjJ6gdhuoDX69Tkw&edm=APs17CUBAAAA&ccb=7-5&oh=00_Af1EmdlOGyKM8yt99O5tCGENFWJ-bCvLPV3NpK6nPkvdMQ&oe=69E27010&_nc_sid=10d13b",
      "analyse": {
        "score": 8,
        "recommande": true,
        "style": "sport",
        "raison": "Contenu fitness avec mouvements d'abdos simples, durée parfaite, regard caméra engageant, hook visuel fort sur la transformation physique",
        "conseil_kling": "Filmer une femme en tenue de sport faisant des exercices d'abdos basiques, mouvements de crunch répétitifs, regard caméra entre les séries, éclairage naturel, transition subtile pour montrer les résultats"
      }
    },
    {
      "username": "karen.katc",
      "url": "https://www.instagram.com/p/DW7C4maAA1Y/",
      "views": 69571,
      "duration": 14.066,
      "caption": "Santorini😍❤️",
      "thumbnail": "https://scontent-atl3-3.cdninstagram.com/v/t51.71878-15/669025278_2400087977120241_5268162297355613461_n.jpg?stp=dst-jpg_e15_tt6&_nc_ht=scontent-atl3-3.cdninstagram.com&_nc_cat=109&_nc_oc=Q6cZ2gExRJmMulV1I7HyHYsN9XBwt1UFF7c45YD8KxUWPOxfihxPIbsmG0oVf1Y4lWe2YKQ&_nc_ohc=SV4wE3wF8SUQ7kNvwEAAuSz&_nc_gid=nOpnkc9o_O2OsVhhkQI1jw&edm=APs17CUBAAAA&ccb=7-5&oh=00_Af3pq8WAVx2iH-1tf_mXNY272kVx12abD-2PjkRLxCurww&oe=69E273FA&_nc_sid=10d13b",
      "analyse": {
        "score": 8,
        "recommande": true,
        "style": "lifestyle",
        "raison": "Contenu voyage lifestyle avec belle vue Santorin, durée parfaite, mouvement simple de modèle posant face caméra, potentiel viral fort avec destination prisée",
        "conseil_kling": "Générer plan fixe ou légèrement mobile d'une femme posant naturellement face caméra avec arrière-plan Santorin/mer bleue, mouvements subtils de cheveux au vent et regard caméra confiant"
      }
    },
    {
      "username": "karen.katc",
      "url": "https://www.instagram.com/p/DV9gCMsAH2b/",
      "views": 50152,
      "duration": 12.446,
      "caption": "",
      "thumbnail": "https://scontent-hou1-1.cdninstagram.com/v/t51.71878-15/653937826_911781765095770_3483103401223215752_n.jpg?stp=dst-jpg_e15_tt6&_nc_ht=scontent-hou1-1.cdninstagram.com&_nc_cat=110&_nc_oc=Q6cZ2gENO21b0UX4lcagp1KZq-DDb96znL_6TQFLd1Mh3lMLpjUZeILVmOcUIgq0sQiTANU&_nc_ohc=yRVR2BOK7lgQ7kNvwGns1Tm&_nc_gid=WoCLchQP5Q7t92Spjrp3sw&edm=APs17CUBAAAA&ccb=7-5&oh=00_Af1ysQvvjFXHnink-ZkDXlwpbF_eanIbF7XCOc5a9Vfztg&oe=69E26740&_nc_sid=10d13b",
      "analyse": {
        "score": 8,
        "recommande": true,
        "style": "lifestyle",
        "raison": "Durée parfaite, mouvement simple et reproductible, style lifestyle approprié, bon potentiel viral avec regard caméra direct",
        "conseil_kling": "Créer un mouvement de caméra fluide en plan rapproché sur le visage, avec transition douce et regard caméra maintenu, utiliser motion control pour le mouvement de tête subtil"
      }
    },
    {
      "username": "julia_delenes22",
      "url": "https://www.instagram.com/p/DW6VNP6Ahwi/",
      "views": 17478,
      "duration": 7.8,
      "caption": "Au moins j’ai essayer",
      "thumbnail": "https://scontent-ord5-2.cdninstagram.com/v/t51.71878-15/670311051_4493459820885194_3750692554388727736_n.jpg?stp=dst-jpg_e15_tt6&_nc_ht=scontent-ord5-2.cdninstagram.com&_nc_cat=102&_nc_oc=Q6cZ2gFUCDGFxODMu2Z-A_Esvh8X2fbFrXzqx1pWMC1C9aEz6aYENueA3HZwiIBbGl8nmxI&_nc_ohc=DpMPcacXpukQ7kNvwFPMYbO&_nc_gid=WTilvEesTySi71kwcFOE6g&edm=APs17CUBAAAA&ccb=7-5&oh=00_Af1S2DcZXb8Ve4zXBSl4-YhLR3Ri0UGdiDoPVN6IiTOZrw&oe=69E27298&_nc_sid=10d13b",
      "analyse": {
        "score": 8,
        "recommande": true,
        "style": "sport",
        "raison": "Vidéo courte et efficace montrant une tentative sportive avec un résultat inattendu, génère de l'empathie et du divertissement. Bon potentiel viral avec le concept 'fail' relatable.",
        "conseil_kling": "Filmer une personne en plan moyen tentant un exercice ou mouvement sportif, utiliser motion control pour créer un mouvement fluide puis un arrêt brusque ou changement de direction pour simuler l'échec de manière humoristique"
      }
    },
    {
      "username": "julia_delenes22",
      "url": "https://www.instagram.com/p/DWt3KHugp-V/",
      "views": 21548,
      "duration": 5.083,
      "caption": "Quand tu veux mettre tes cheveux en valeur après le coiffeur >>",
      "thumbnail": "https://scontent-lga3-2.cdninstagram.com/v/t51.71878-15/659342463_958853280223296_8417389774236665261_n.jpg?stp=dst-jpg_e15_tt6&_nc_ht=scontent-lga3-2.cdninstagram.com&_nc_cat=100&_nc_oc=Q6cZ2gHMv7FgZmBioicn22c7PBs8NAyW8jJktvQXlBUi7BYN7qVezw7YtW8KenhjencpE-A&_nc_ohc=2aafF1Zg_DIQ7kNvwEBIjEJ&_nc_gid=chzL1ZcAfigTRKoCeYGyJA&edm=APs17CUBAAAA&ccb=7-5&oh=00_Af1xV0oC05D35eh_QsIAVzK72fQF6j5mDidW6vzgCdx3Gg&oe=69E27D64&_nc_sid=10d13b",
      "analyse": {
        "score": 8,
        "recommande": true,
        "style": "lifestyle",
        "raison": "Excellent contenu lifestyle avec mouvement de cheveux simple, durée parfaite, caption en français engageante sur la mise en valeur après coiffeur. Hook visuel fort avec regard caméra probable.",
        "conseil_kling": "Générer une femme brune regardant la caméra, mouvement fluide des cheveux de gauche à droite ou rotation de tête lente, éclairage doux, expression confiante et souriante"
      }
    },
    {
      "username": "julia_delenes22",
      "url": "https://www.instagram.com/p/DW1lvzTgrjD/",
      "views": 86202,
      "duration": 6.152,
      "caption": "L’après sport",
      "thumbnail": "https://instagram.flas1-1.fna.fbcdn.net/v/t51.71878-15/661563524_2168886417277174_4817421101158853875_n.jpg?stp=dst-jpg_e15_tt6&_nc_ht=instagram.flas1-1.fna.fbcdn.net&_nc_cat=110&_nc_oc=Q6cZ2gGWN4oWPOWtvpI42XUiwUtyDz-tZVUidf2po2Yoo-U9fTBA3wwoXaOJ5yUnkqudwGs&_nc_ohc=lAHxyfyU6R8Q7kNvwG5IRH_&_nc_gid=K579QVCEJrIyfP84Bh7WLg&edm=APs17CUBAAAA&ccb=7-5&oh=00_Af0eU7GhkMg5X15nEc-zqNJyCgCyDCTkWfir-LKG5wb8kw&oe=69E27C57&_nc_sid=10d13b",
      "analyse": {
        "score": 8,
        "recommande": true,
        "style": "sport",
        "raison": "Excellent contenu après-sport avec durée parfaite (6.15s), style lifestyle sport très tendance, mouvement simple reproductible, potentiel viral élevé avec 86k vues",
        "conseil_kling": "Reproduire avec motion control simple : modèle en tenue de sport qui ajuste ses cheveux ou s'étire après l'effort, mouvement fluide des bras et léger balancement du corps, focus sur l'expression de satisfaction post-workout"
      }
    },
    {
      "username": "julia_delenes22",
      "url": "https://www.instagram.com/p/DWjhPs7gjRt/",
      "views": 23563,
      "duration": 8.127,
      "caption": "Quand t’es 100% naturel sans maquillage juste toi et tes tache de roux sœurs",
      "thumbnail": "https://scontent-mia3-2.cdninstagram.com/v/t51.71878-15/658064190_1306638174724471_3209828892086429524_n.jpg?stp=dst-jpg_e15_tt6&_nc_ht=scontent-mia3-2.cdninstagram.com&_nc_cat=107&_nc_oc=Q6cZ2gFmDDPahc090BVWO8rjPxoYucc7eN-DBwpz1-2N46_0BfDUQjEZPN7Mjpqmja1JpVs&_nc_ohc=w4CZfGXHBl4Q7kNvwHK2duA&_nc_gid=c5CRUMmFYl9Bz4meDU53fA&edm=APs17CUBAAAA&ccb=7-5&oh=00_Af1aphwisuHZa2629tv2PP63leulwwUBk7bw8uh44mBl3g&oe=69E275A4&_nc_sid=10d13b",
      "analyse": {
        "score": 8,
        "recommande": true,
        "style": "lifestyle",
        "raison": "Contenu authentique sans maquillage avec message body-positive, durée parfaite, regard caméra fort, très reproductible",
        "conseil_kling": "Portrait statique ou léger mouvement de tête, focus sur le visage naturel, éclairage doux, expression confiante vers caméra"
      }
    },
    {
      "username": "julia_delenes22",
      "url": "https://www.instagram.com/p/DW4DpcrAl2h/",
      "views": 29837,
      "duration": 7.547,
      "caption": "Quand tu vas dire bonjour au mec de ta petite sœur et qu’il bagaye dans son bonjour",
      "thumbnail": "https://scontent-sea5-1.cdninstagram.com/v/t51.71878-15/658059695_1276724127154819_5901699686251578703_n.jpg?stp=dst-jpg_e15_tt6&_nc_ht=scontent-sea5-1.cdninstagram.com&_nc_cat=107&_nc_oc=Q6cZ2gFYxo7C6K2ivViqTLgZ8UcKal-MPfy5s5jNYb6Bpouw9N3AoZGCBLpaSHJT0ky7niM&_nc_ohc=Z37d7Ln-_McQ7kNvwG-0aVL&_nc_gid=zAhHV0BrLG-Y7gix1CIx6g&edm=APs17CUBAAAA&ccb=7-5&oh=00_Af3UJqownSLLDWL_c0JImKeYiVWr7xKLfPkTUQ5md3-Rtw&oe=69E269A1&_nc_sid=10d13b",
      "analyse": {
        "score": 8,
        "recommande": true,
        "style": "chill",
        "raison": "Concept viral avec regard caméra intense, durée parfaite, contenu français relatif. Expression faciale forte et situation humoristique universelle.",
        "conseil_kling": "Gros plan visage femme, transition expression neutre vers regard intense/dominateur, léger zoom avant, éclairage naturel, mouvement subtil des yeux et sourcils"
      }
    },
    {
      "username": "annatomaax",
      "url": "https://www.instagram.com/p/DWyvYFnDOre/",
      "views": 122862,
      "duration": 4.133,
      "caption": "Tu préfères quoi ? 🫶🏼\n.\n.\n.\n#blonde #humour #yeuxbleu",
      "thumbnail": "https://scontent-ord5-2.cdninstagram.com/v/t51.71878-15/660991897_1272230475056873_7819612920400836355_n.jpg?stp=dst-jpg_e15_tt6&_nc_ht=scontent-ord5-2.cdninstagram.com&_nc_cat=105&_nc_oc=Q6cZ2gHXNmfBTQcXuTWXCQpqo1z1z5Z-A0H8AAH0onQV7-6xWJk8T4YCb7V2ji7wQRi2y7o&_nc_ohc=Q4Ij-NH_rjEQ7kNvwGE-E7L&_nc_gid=Wo_ApsCtotf5e2yvYlalZA&edm=APs17CUBAAAA&ccb=7-5&oh=00_Af2RVlfe78KvqVESaPRa8r57wbHsX6tlO3OBIsfqlnvj-A&oe=69E26532&_nc_sid=10d13b",
      "analyse": {
        "score": 8,
        "recommande": true,
        "style": "lifestyle",
        "raison": "Durée parfaite, format question engageant, regard caméra direct, mouvement simple de présentation, style lifestyle français approprié",
        "conseil_kling": "Créer un plan fixe avec modèle face caméra, légers mouvements de tête et expressions faciales changeantes, overlay texte pour la question, transition douce entre 2-3 poses/expressions"
      }
    },
    {
      "username": "clari_cremaschi",
      "url": "https://www.instagram.com/p/DWXB-1DOr40/",
      "views": 712891,
      "duration": 12.398,
      "caption": "😼🤝",
      "thumbnail": "https://scontent-phl2-1.cdninstagram.com/v/t51.82787-15/659024121_17883496770496550_2910241514086542348_n.jpg?stp=dst-jpg_e15_tt6&_nc_ht=scontent-phl2-1.cdninstagram.com&_nc_cat=102&_nc_oc=Q6cZ2gHZJLErBdczp5-XB3tiKTpEYp9XbDjNq6ySD5M0VfLbzoS0xNDWp35QxD3K2b43iwQ&_nc_ohc=lpkND9PtUBkQ7kNvwEttbRP&_nc_gid=leEMX7u5Gc6hB6hJ6Nazng&edm=APs17CUBAAAA&ccb=7-5&oh=00_Af0978qoRmsVyJWawyKBs9AkAD25OJjge7Xm4Pe8mVmk5g&oe=69E27EB3&_nc_sid=10d13b",
      "analyse": {
        "score": 8,
        "recommande": true,
        "style": "lifestyle",
        "raison": "Excellent potentiel viral avec regard caméra intense, durée parfaite, mouvement simple reproductible, style lifestyle approprié",
        "conseil_kling": "Créer un plan fixe avec modèle regardant directement la caméra, expression confiante/séductrice, léger mouvement de tête ou cheveux, éclairage naturel, transition fluide d'une expression à l'autre"
      }
    },
    {
      "username": "clari_cremaschi",
      "url": "https://www.instagram.com/p/DQS1KOpDOqX/",
      "views": 3235209,
      "duration": 5.466,
      "caption": "PORQUEEE😭😏",
      "thumbnail": "https://scontent-ord5-3.cdninstagram.com/v/t51.71878-15/572096765_1416037793463840_7616924854693611933_n.jpg?stp=dst-jpg_e15_tt6&_nc_ht=scontent-ord5-3.cdninstagram.com&_nc_cat=100&_nc_oc=Q6cZ2gEBBPluR83MvwRnxKfhCBa1VgawvoTiShkDfrqZNzSro8ppMmO1qOlGtKrlo7ru83c&_nc_ohc=MeomUJdvjw8Q7kNvwEK1kOl&_nc_gid=JL0rywoPQ7v9iaa_3rUM_Q&edm=APs17CUBAAAA&ccb=7-5&oh=00_Af0sEPdOnnG0vkITUUsFIejUwr16bj65KOlUzc6CwqpErg&oe=69E25E98&_nc_sid=10d13b",
      "analyse": {
        "score": 8,
        "recommande": true,
        "style": "lifestyle",
        "raison": "Durée parfaite, expressions faciales captivantes avec regard caméra direct, mouvement simple de réaction émotionnelle très engageant",
        "conseil_kling": "Générer une jeune femme brune regardant la caméra avec expressions changeantes (surprise puis sourire malicieux), mouvement subtil de tête et jeu de regard, arrière-plan neutre"
      }
    },
    {
      "username": "clari_cremaschi",
      "url": "https://www.instagram.com/p/DLvjnsApRQr/",
      "views": 5479292,
      "duration": 7.166,
      "caption": "😎🫵🏽",
      "thumbnail": "https://scontent-ord5-1.cdninstagram.com/v/t51.71878-15/504375244_1708065109897487_7045876959012831445_n.jpg?stp=dst-jpg_e15_tt6&_nc_ht=scontent-ord5-1.cdninstagram.com&_nc_cat=111&_nc_oc=Q6cZ2gFRuh-A6CiQ6sMYYDLn1E4m1X32XNPBT_dwaJSlhUCrD9kcbTJ5OnzDuTbtp6jRZOQ&_nc_ohc=CcweTnXkqZ8Q7kNvwH4CWeC&_nc_gid=Go2BbVnFUGX3eFlMqZpxmw&edm=APs17CUBAAAA&ccb=7-5&oh=00_Af0t03C5AP8HTefS-f7CIRSMGZ9BZWe0EZpY4IfSHGdbmw&oe=69E275FB&_nc_sid=10d13b",
      "analyse": {
        "score": 8,
        "recommande": true,
        "style": "chill",
        "raison": "Durée parfaite (7s), mouvement simple de pointage vers caméra avec lunettes de soleil, regard caméra direct très engageant, style décontracté reproductible",
        "conseil_kling": "Générer un portrait femme avec lunettes de soleil, mouvement lent de bras qui pointe vers caméra, regard fixe caméra, expression confiante, arrière-plan flou neutre"
      }
    },
    {
      "username": "clari_cremaschi",
      "url": "https://www.instagram.com/p/DHWz7hHp0GD/",
      "views": 3376163,
      "duration": 11,
      "caption": "🤪",
      "thumbnail": "https://scontent-ord5-3.cdninstagram.com/v/t51.71878-15/485094009_3953364508210204_2324379009432679197_n.jpg?stp=dst-jpg_e15_tt6&_nc_ht=scontent-ord5-3.cdninstagram.com&_nc_cat=104&_nc_oc=Q6cZ2gHgwlxUXRMsGKhulKjq-z6XQdChwcRzAzSvwbplCOg2RXAQF3GwtB-anBwGRu4PRd8&_nc_ohc=Tdk-h1XPR9AQ7kNvwFNyRRt&_nc_gid=OEJdgbdd_c0YChUKzSZntw&edm=APs17CUBAAAA&ccb=7-5&oh=00_Af0Qnt0l8zk6gNgkmXe3mZzcqnGucPn33xfXnnufWxviwg&oe=69E26F1E&_nc_sid=10d13b",
      "analyse": {
        "score": 8,
        "recommande": true,
        "style": "lifestyle",
        "raison": "Mouvement simple et reproductible, regard caméra engageant, durée parfaite de 11s, style lifestyle décontracté avec potentiel viral élevé",
        "conseil_kling": "Créer un mouvement de regard caméra avec expression faciale changeante, transition douce entre différentes expressions, contrôler le mouvement de tête et des cheveux pour un effet naturel"
      }
    },
    {
      "username": "dahyn1xoficial",
      "url": "https://www.instagram.com/p/DXC4-0LjpxP/",
      "views": 12500,
      "duration": 13.77,
      "caption": "😏 hey \n\n.\n\n.\n\n.\n\n.\n#reels #eeuu #girl #cute #bellydance",
      "thumbnail": "https://scontent-den2-1.cdninstagram.com/v/t51.71878-15/670146407_1317590050276413_4565440097550489380_n.jpg?stp=dst-jpg_e15_tt6&_nc_ht=scontent-den2-1.cdninstagram.com&_nc_cat=109&_nc_oc=Q6cZ2gHAp7nwFpKmxboanxQOhbpIe-jtmzlUpeyIp3wuNWyQHZR8CgNUV1u8SyH-UYXvUc4&_nc_ohc=DX-pilk0YvoQ7kNvwFeiKAG&_nc_gid=MNONf92Pe1XO6cIn1HPJYA&edm=APs17CUBAAAA&ccb=7-5&oh=00_Af2_rdyUGFI7hOHvW8tuSHK7le7lxJzfZ_IizWtCLl6mcQ&oe=69E2784E&_nc_sid=10d13b",
      "analyse": {
        "score": 7,
        "recommande": true,
        "style": "danse",
        "raison": "Belly dance avec mouvements fluides, durée parfaite, regard caméra engageant, style approprié pour OFM lifestyle",
        "conseil_kling": "Utiliser motion control pour mouvements de hanches et bras fluides, focus sur le regard caméra, éclairage doux, cadrage buste/taille"
      }
    },
    {
      "username": "karen.katc",
      "url": "https://www.instagram.com/p/DSyfl41DRJV/",
      "views": 225026,
      "duration": 14.1,
      "caption": "",
      "thumbnail": "https://scontent-ord5-1.cdninstagram.com/v/t51.71878-15/606662662_875578851530555_1902839661961874532_n.jpg?stp=dst-jpg_e15_tt6&_nc_ht=scontent-ord5-1.cdninstagram.com&_nc_cat=111&_nc_oc=Q6cZ2gFhbVLwfdF0psLd6HBbPJk6TiATsboRyTS-V7iGlxTgrG-wetVQeDGXJdKu5pDk0Hs&_nc_ohc=UWZ8ArtykeUQ7kNvwFbD-OE&_nc_gid=TPEmm5zQTP2_xtERHcO7Dg&edm=APs17CUBAAAA&ccb=7-5&oh=00_Af1ecByHoLJd8ukElm714sjiJ8b0iJqwl7Ov0BSJJvSZTw&oe=69E268E3&_nc_sid=10d13b",
      "analyse": {
        "score": 7,
        "recommande": true,
        "style": "lifestyle",
        "raison": "Durée parfaite 14.1s, mouvement simple reproductible, style lifestyle élégant avec regard caméra engageant et bon potentiel viral",
        "conseil_kling": "Utiliser motion control pour mouvement fluide de cheveux et léger balancement du corps, focus sur le regard caméra avec transition douce d'expression"
      }
    },
    {
      "username": "karen.katc",
      "url": "https://www.instagram.com/p/DW9XpmYDYdq/",
      "views": 46880,
      "duration": 10.82,
      "caption": "",
      "thumbnail": "https://scontent-ord5-3.cdninstagram.com/v/t51.71878-15/670828640_1330496532474595_839633436719045833_n.jpg?stp=dst-jpg_e15_tt6&_nc_ht=scontent-ord5-3.cdninstagram.com&_nc_cat=107&_nc_oc=Q6cZ2gHwJCSpPPAED7Nqg-0UoQy6C74YErV8w5_xQLx-fC-js7blY3xEwBYAbdVMP-RLORk&_nc_ohc=Aahl6BfSaucQ7kNvwFmWjkz&_nc_gid=D1e47nmE1C6keQRLrxmXKg&edm=APs17CUBAAAA&ccb=7-5&oh=00_Af0AFKHXCONg4BQA5znPs7lsNPxlt3VVkO6XCN5bTYImaw&oe=69E266BF&_nc_sid=10d13b",
      "analyse": {
        "score": 7,
        "recommande": true,
        "style": "lifestyle",
        "raison": "Durée parfaite, mouvement simple reproductible, style lifestyle approprié, bon potentiel viral avec regard caméra direct",
        "conseil_kling": "Générer une femme brune regardant directement la caméra avec expression confiante, mouvement subtil de cheveux et léger sourire, éclairage naturel doux"
      }
    },
    {
      "username": "julia_delenes22",
      "url": "https://www.instagram.com/p/DXCVyzdiA6V/",
      "views": 9286,
      "duration": 5.945,
      "caption": "Pov tu croise deux mecs qui te disent que t’es moches donc t essaye de faire genre que t’es pas vexe",
      "thumbnail": "https://scontent-ord5-3.cdninstagram.com/v/t51.71878-15/670479991_1320087829973551_7257917013871679268_n.jpg?stp=dst-jpg_e15_tt6&_nc_ht=scontent-ord5-3.cdninstagram.com&_nc_cat=107&_nc_oc=Q6cZ2gFz0ETmdBb3iu4wP2Pc0NudA2-qWyiRq7xKYE1bPgL1srHpG-4veehF4zKwfJeMAB4&_nc_ohc=Yg-0SH3P_YIQ7kNvwFB1H20&_nc_gid=YD8i-Vu6uCNWTLMnE0Im4Q&edm=APs17CUBAAAA&ccb=7-5&oh=00_Af0m-Pl5SVDEeoLer9agx5QMG8gx8As2vE9qbnYcvL15Fg&oe=69E268E0&_nc_sid=10d13b",
      "analyse": {
        "score": 7,
        "recommande": true,
        "style": "lifestyle",
        "raison": "Contenu relatable avec émotion claire, durée parfaite, concept viral sur l'insécurité féminine",
        "conseil_kling": "Filmer une jeune femme qui fait semblant de sourire/rire de manière forcée en regardant la caméra, puis transition vers expression plus neutre/triste"
      }
    },
    {
      "username": "julia_delenes22",
      "url": "https://www.instagram.com/p/DWy99i6gs1P/",
      "views": 19131,
      "duration": 8.382,
      "caption": "Moi et ma chienne",
      "thumbnail": "https://scontent-atl3-3.cdninstagram.com/v/t51.71878-15/662307226_2771952639806839_2259953082264620240_n.jpg?stp=dst-jpg_e15_tt6&_nc_ht=scontent-atl3-3.cdninstagram.com&_nc_cat=107&_nc_oc=Q6cZ2gHKYW8gEZ0l7nid0pVQDzTortvCLBOILpU1tEIfICijmP1G9x2Cd_MPCcB55C-7Hmo&_nc_ohc=OhUBvv1h0oEQ7kNvwGUwh_A&_nc_gid=LnIDE3G_Oqmh2Nn0xCPOXg&edm=APs17CUBAAAA&ccb=7-5&oh=00_Af3XhOhewyv1nCJOrWa9_ZFPvZlUFZxogos5Y2lhS7JkMA&oe=69E26BF0&_nc_sid=10d13b",
      "analyse": {
        "score": 7,
        "recommande": true,
        "style": "lifestyle",
        "raison": "Contenu mignon avec chien, durée parfaite, mouvement simple, potentiel viral fort pour les amoureux d'animaux",
        "conseil_kling": "Générer une jeune femme souriante tenant un petit chien dans ses bras, mouvement de caresse douce, regard caméra avec expression attendrie, arrière-plan intérieur chaleureux"
      }
    },
    {
      "username": "julia_delenes22",
      "url": "https://www.instagram.com/p/DWqy_BTAqvC/",
      "views": 17087,
      "duration": 7.8,
      "caption": "Tu repense à quand tu avais etait loin de chez toi pour la première fois en vacances et que tout les",
      "thumbnail": "https://instagram.fhsv1-1.fna.fbcdn.net/v/t51.71878-15/658371841_2251433175264828_8819998551396048979_n.jpg?stp=dst-jpg_e15_tt6&_nc_ht=instagram.fhsv1-1.fna.fbcdn.net&_nc_cat=100&_nc_oc=Q6cZ2gFY7Eqwb7ZbGO3AzS9ylLGdhxX0bMjZpyZnxu_o3HvtjSiAH7IgKtmvqbBRjy_PBXs&_nc_ohc=OkABPKkeWFoQ7kNvwGxEgeM&_nc_gid=sD9MWLcyt6XbjXlcXWGrqg&edm=APs17CUBAAAA&ccb=7-5&oh=00_Af0_bKTgR-_9kXhI4fFVSKCufGYhe9ytoyemrx7Gpjh25Q&oe=69E26CFE&_nc_sid=10d13b",
      "analyse": {
        "score": 7,
        "recommande": true,
        "style": "chill",
        "raison": "Contenu nostalgique relatif aux vacances, durée parfaite 7.8s, style lifestyle chill approprié pour le marché français",
        "conseil_kling": "Créer une séquence simple avec regard contemplatif vers la caméra, expression nostalgique, mouvement léger de tête ou changement subtil d'expression pour évoquer les souvenirs de vacances"
      }
    },
    {
      "username": "annatomaax",
      "url": "https://www.instagram.com/p/DXCDn6xjHZI/",
      "views": 9022,
      "duration": 9.133,
      "caption": "Aide moi ! 🩵\n.\n.\n.\n#blonde #humour #yeuxbleu #photo #talons",
      "thumbnail": "https://scontent-mia5-1.cdninstagram.com/v/t51.71878-15/670410122_26091303597235597_6753996439056808385_n.jpg?stp=dst-jpg_e15_tt6&_nc_ht=scontent-mia5-1.cdninstagram.com&_nc_cat=101&_nc_oc=Q6cZ2gG1anwiC95rVx0OcxGu-0EIz9V20mgR0-XXLI5P3k4O_PPCIhZUmoeenpxF-l9js7U&_nc_ohc=8oAlg2e_RygQ7kNvwHu8q6R&_nc_gid=Z12DiZN4QzcUTQ3zL4pc7Q&edm=APs17CUBAAAA&ccb=7-5&oh=00_Af0Aed31owU4BnWtFKKbC9OUrboLsZ-g5U9Vntf6tSJ30Q&oe=69E272DD&_nc_sid=10d13b",
      "analyse": {
        "score": 7,
        "recommande": true,
        "style": "lifestyle",
        "raison": "Durée parfaite, mouvement simple reproductible, style lifestyle approprié avec regard caméra engageant",
        "conseil_kling": "Utiliser motion control pour mouvement subtle de tête et regard caméra, focus sur expression faciale et gestuelle des mains, fond neutre pour faciliter le rendu"
      }
    }
  ]
}