{
  "date": "2026-04-14T08:12:52.431110",
  "total": 63,
  "recommandes": 4,
  "reels": [
    {
      "username": "joellperry",
      "url": "https://www.instagram.com/p/DWu5ivQlbZJ/",
      "views": 41291,
      "duration": 11.77,
      "caption": "look at my cherry shirt! 🍒\n.\n.\n.\n.\n.\n.\n.\n.\n.\n.\n.\n.\n.\n.\n.\n.\n.\n.\n.\n.\n.\n.\n.\n.\n.\n.\n.\n.\n.\n.\n.\n.\n.\n.\n.\n.\n.",
      "thumbnail": "https://scontent-atl3-1.cdninstagram.com/v/t51.71878-15/658786549_25785726274438890_4747026648845973436_n.jpg?stp=dst-jpg_e15_tt6&_nc_ht=scontent-atl3-1.cdninstagram.com&_nc_cat=106&_nc_oc=Q6cZ2gHmizfkiPNRX06xJjK1eMIEC80zr94F67tbOKIycwvLSrTfTtoP3xcl1Ms3RHYk42U&_nc_ohc=YBOcCcXqhCUQ7kNvwGtbeV9&_nc_gid=xnqg77qCLN7oJs3tWLC7Ow&edm=APs17CUBAAAA&ccb=7-5&oh=00_Af0upkE57ozcKHooEunQyQU_JI2Q7qqLTHSoPSicjHGTgQ&oe=69E3B2CA&_nc_sid=10d13b",
      "analyse": {
        "score": 7,
        "recommande": true,
        "style": "lifestyle",
        "raison": "Contenu lifestyle simple avec focus sur un vêtement, durée adaptée, mouvement reproductible et potentiel viral correct",
        "conseil_kling": "Générer une femme qui montre/présente un t-shirt à motif cerises avec des mouvements simples de présentation face caméra, éclairage naturel, plan rapproché buste"
      }
    },
    {
      "username": "julia_delenes22",
      "url": "https://www.instagram.com/p/DWwnl0IglJ9/",
      "views": 15435,
      "duration": 14.118,
      "caption": "",
      "thumbnail": "https://scontent-atl3-2.cdninstagram.com/v/t51.71878-15/658913799_1693863795391466_5388749299583807061_n.jpg?stp=dst-jpg_e15_tt6&_nc_ht=scontent-atl3-2.cdninstagram.com&_nc_cat=102&_nc_oc=Q6cZ2gFlBUY84zI31bhIWNPUdhvPDE1qLxpRK0VQuZPrUGHkvyP4NwlNCe032nieaU8ny7c&_nc_ohc=iYlwVB7BLjwQ7kNvwHIUxLz&_nc_gid=swMp5QPBP4mFGTR94YfLQA&edm=APs17CUBAAAA&ccb=7-5&oh=00_Af0L0Q2wGAa-H3F8v9iA6FGLqqWvZ1wXm0wHgC2CRTRCJg&oe=69E3B40C&_nc_sid=10d13b",
      "analyse": {
        "score": 7,
        "recommande": true,
        "style": "lifestyle",
        "raison": "Durée parfaite (14s), style lifestyle approprié, mouvement simple reproductible, bon potentiel viral avec regard caméra",
        "conseil_kling": "Utiliser motion control pour mouvement de tête léger et regard caméra direct, plan fixe avec légère rotation, focus sur expression faciale naturelle"
      }
    },
    {
      "username": "julia_delenes22",
      "url": "https://www.instagram.com/p/DWqy_BTAqvC/",
      "views": 17488,
      "duration": 7.8,
      "caption": "Tu repense à quand tu avais etait loin de chez toi pour la première fois en vacances et que tout les",
      "thumbnail": "https://scontent-atl3-1.cdninstagram.com/v/t51.71878-15/658371841_2251433175264828_8819998551396048979_n.jpg?stp=dst-jpg_e15_tt6&_nc_ht=scontent-atl3-1.cdninstagram.com&_nc_cat=100&_nc_oc=Q6cZ2gH54KIUYjxbWW4fPwqaFeD0WsHkSH5qRhy_vXthSm8Mm9sW0w-NjEQs6vTb4iNmksI&_nc_ohc=ewUY2iRrbNAQ7kNvwGxrlCk&_nc_gid=BwKrnRht0aR-u9DsX_qLKQ&edm=APs17CUBAAAA&ccb=7-5&oh=00_Af3X0OoxN6114BhVdV6xU3jgbmFwszUIrZC5mTter_bFug&oe=69E3BE7E&_nc_sid=10d13b",
      "analyse": {
        "score": 7,
        "recommande": true,
        "style": "lifestyle",
        "raison": "Contenu nostalgique avec regard caméra direct, durée optimale et thématique relationnelle forte pour audience française",
        "conseil_kling": "Plan fixe buste, jeune femme regard caméra avec micro-expressions nostalgiques/émotionnelles, transition subtile d'expression neutre vers sourire mélancolique"
      }
    },
    {
      "username": "julia_delenes22",
      "url": "https://www.instagram.com/p/DWjhPs7gjRt/",
      "views": 23889,
      "duration": 8.127,
      "caption": "Quand t’es 100% naturel sans maquillage juste toi et tes tache de roux sœurs",
      "thumbnail": "https://scontent-lga3-2.cdninstagram.com/v/t51.71878-15/658064190_1306638174724471_3209828892086429524_n.jpg?stp=dst-jpg_e15_tt6&_nc_ht=scontent-lga3-2.cdninstagram.com&_nc_cat=107&_nc_oc=Q6cZ2gE4Wto4dgRe4rjHoSbDdaPxOI1-6RLqgfAoQ-XAAJ1pxSgAIGK8dqSPAvnT4QHnfzg&_nc_ohc=w4CZfGXHBl4Q7kNvwHwXd8q&_nc_gid=hdw6TaHvTMvy5coRKA3s2g&edm=APs17CUBAAAA&ccb=7-5&oh=00_Af15dy_pVyV5KhaMPMiFf8YfbG9nZujQGovvuqiLFa538w&oe=69E3C724&_nc_sid=10d13b",
      "analyse": {
        "score": 7,
        "recommande": true,
        "style": "lifestyle",
        "raison": "Portrait naturel avec message body-positive, durée parfaite, regard caméra engageant, mouvement simple reproductible",
        "conseil_kling": "Portrait fixe d'une femme rousse regardant la caméra avec léger mouvement de tête et sourire naturel, éclairage doux, fond neutre, expression confiante et authentique"
      }
    }
  ]
}